CONTRIBUTING.md
LICENSE
MANIFEST.in
README.md
requirements.txt
setup.py
netcdf_flattener/__init__.py
netcdf_flattener/flatten.py
test/base_test.py
test/test_cell_methods.py
test/test_flatten.py
test/test_grid_mapping.py
test/test_long_names.py
test/test_slicing.py
test/test_strict_lax.py
test/data/input1.cdl
test/data/input2.cdl
test/data/input3.cdl
test/data/input4.cdl
test/data/input5.cdl
test/data/input6.cdl
test/data/reference1.cdl
test/data/reference2.cdl
test/data/reference3.cdl
test/data/reference4.cdl
test/data/reference5.cdl
test/data/reference6.cdl