Metadata-Version: 2.1
Name: netcdf-flattener
Version: 1.0.1b6
Summary: The NetCDF-flattener package
Home-page: https://gitlab.eumetsat.int/additional-data-services/netcdf-flattener
Author: Guillaume Obrecht
Author-email: guillaume.obrecht@c-ssystems.de
License: UNKNOWN
Platform: UNKNOWN
Classifier: Programming Language :: Python :: 3
Classifier: License :: OSI Approved :: Apache Software License
Classifier: Operating System :: OS Independent
